Workbook

Sheet Sales_Data
A1: Order_ID | B1: Date | C1: Salesperson | D1: Region | E1: Category | F1: Product | G1: Quantity | H1: Unit_Price | I1: Discount_% | J1: Revenue | K1: Cost | L1: Profit
A2: 1 | B2: 2024-01-08 | C2: Bob | D2: North | E2: Electronics | F2: Laptop | G2: 9 | H2: 1200 | I2: 5 | J2: =G2*H2*(1-I2/100) -> 10260 | K2: =G2*720 -> 6480 | L2: =J2-K2 -> 3780
A3: 2 | B3: 2024-01-19 | C3: David | D3: North | E3: Food | F3: Cookies | G3: 18 | H3: 8 | I3: 0 | J3: =G3*H3*(1-I3/100) -> 144 | K3: =G3*4.8 -> 86.4 | L3: =J3-K3 -> 57.6
A4: 3 | B4: 2024-01-17 | C4: Eva | D4: North | E4: Electronics | F4: Laptop | G4: 7 | H4: 1200 | I4: 5 | J4: =G4*H4*(1-I4/100) -> 7980 | K4: =G4*720 -> 5040 | L4: =J4-K4 -> 2940
A5: 4 | B5: 2024-01-08 | C5: David | D5: East | E5: Food | F5: Coffee | G5: 18 | H5: 15 | I5: 15 | J5: =G5*H5*(1-I5/100) -> 229.5 | K5: =G5*9 -> 162 | L5: =J5-K5 -> 67.5
A6: 5 | B6: 2024-01-09 | C6: Bob | D6: South | E6: Electronics | F6: Laptop | G6: 14 | H6: 1200 | I6: 10 | J6: =G6*H6*(1-I6/100) -> 15120 | K6: =G6*720 -> 10080 | L6: =J6-K6 -> 5040
A7: 6 | B7: 2024-01-04 | C7: Carol | D7: East | E7: Clothing | F7: T-Shirt | G7: 3 | H7: 25 | I7: 15 | J7: =G7*H7*(1-I7/100) -> 63.75 | K7: =G7*15 -> 45 | L7: =J7-K7 -> 18.75
A8: 7 | B8: 2024-01-18 | C8: Alice | D8: West | E8: Food | F8: Tea | G8: 2 | H8: 10 | I8: 15 | J8: =G8*H8*(1-I8/100) -> 17 | K8: =G8*6 -> 12 | L8: =J8-K8 -> 5
A9: 8 | B9: 2024-01-28 | C9: Carol | D9: South | E9: Electronics | F9: Tablet | G9: 10 | H9: 400 | I9: 20 | J9: =G9*H9*(1-I9/100) -> 3200 | K9: =G9*240 -> 2400 | L9: =J9-K9 -> 800
A10: 9 | B10: 2024-01-25 | C10: Carol | D10: North | E10: Food | F10: Coffee | G10: 2 | H10: 15 | I10: 5 | J10: =G10*H10*(1-I10/100) -> 28.5 | K10: =G10*9 -> 18 | L10: =J10-K10 -> 10.5
A11: 10 | B11: 2024-01-15 | C11: Carol | D11: South | E11: Electronics | F11: Laptop | G11: 13 | H11: 1200 | I11: 10 | J11: =G11*H11*(1-I11/100) -> 14040 | K11: =G11*720 -> 9360 | L11: =J11-K11 -> 4680
A12: 11 | B12: 2024-01-23 | C12: Alice | D12: South | E12: Clothing | F12: Jeans | G12: 7 | H12: 60 | I12: 10 | J12: =G12*H12*(1-I12/100) -> 378 | K12: =G12*36 -> 252 | L12: =J12-K12 -> 126
A13: 12 | B13: 2024-01-15 | C13: David | D13: East | E13: Food | F13: Cookies | G13: 8 | H13: 8 | I13: 5 | J13: =G13*H13*(1-I13/100) -> 60.8 | K13: =G13*4.8 -> 38.4 | L13: =J13-K13 -> 22.4
A14: 13 | B14: 2024-01-22 | C14: Carol | D14: North | E14: Food | F14: Cookies | G14: 18 | H14: 8 | I14: 5 | J14: =G14*H14*(1-I14/100) -> 136.8 | K14: =G14*4.8 -> 86.4 | L14: =J14-K14 -> 50.4
A15: 14 | B15: 2024-01-09 | C15: Alice | D15: South | E15: Electronics | F15: Laptop | G15: 11 | H15: 1200 | I15: 15 | J15: =G15*H15*(1-I15/100) -> 11220 | K15: =G15*720 -> 7920 | L15: =J15-K15 -> 3300
A16: 15 | B16: 2024-01-21 | C16: David | D16: West | E16: Food | F16: Cookies | G16: 11 | H16: 8 | I16: 5 | J16: =G16*H16*(1-I16/100) -> 83.6 | K16: =G16*4.8 -> 52.8 | L16: =J16-K16 -> 30.8
A17: 16 | B17: 2024-01-05 | C17: Bob | D17: East | E17: Food | F17: Tea | G17: 5 | H17: 10 | I17: 10 | J17: =G17*H17*(1-I17/100) -> 45 | K17: =G17*6 -> 30 | L17: =J17-K17 -> 15
A18: 17 | B18: 2024-01-13 | C18: Carol | D18: South | E18: Food | F18: Cookies | G18: 14 | H18: 8 | I18: 20 | J18: =G18*H18*(1-I18/100) -> 89.6 | K18: =G18*4.8 -> 67.2 | L18: =J18-K18 -> 22.4
A19: 18 | B19: 2024-01-25 | C19: Alice | D19: North | E19: Electronics | F19: Tablet | G19: 16 | H19: 400 | I19: 0 | J19: =G19*H19*(1-I19/100) -> 6400 | K19: =G19*240 -> 3840 | L19: =J19-K19 -> 2560
A20: 19 | B20: 2024-01-20 | C20: Alice | D20: West | E20: Electronics | F20: Tablet | G20: 6 | H20: 400 | I20: 15 | J20: =G20*H20*(1-I20/100) -> 2040 | K20: =G20*240 -> 1440 | L20: =J20-K20 -> 600
A21: 20 | B21: 2024-01-09 | C21: Eva | D21: North | E21: Clothing | F21: Jacket | G21: 15 | H21: 120 | I21: 20 | J21: =G21*H21*(1-I21/100) -> 1440 | K21: =G21*72 -> 1080 | L21: =J21-K21 -> 360
A22: 21 | B22: 2024-01-25 | C22: Carol | D22: East | E22: Food | F22: Cookies | G22: 4 | H22: 8 | I22: 20 | J22: =G22*H22*(1-I22/100) -> 25.6 | K22: =G22*4.8 -> 19.2 | L22: =J22-K22 -> 6.4
A23: 22 | B23: 2024-01-15 | C23: Alice | D23: East | E23: Electronics | F23: Phone | G23: 14 | H23: 600 | I23: 5 | J23: =G23*H23*(1-I23/100) -> 7980 | K23: =G23*360 -> 5040 | L23: =J23-K23 -> 2940
A24: 23 | B24: 2024-01-28 | C24: Carol | D24: South | E24: Food | F24: Coffee | G24: 17 | H24: 15 | I24: 0 | J24: =G24*H24*(1-I24/100) -> 255 | K24: =G24*9 -> 153 | L24: =J24-K24 -> 102
A25: 24 | B25: 2024-01-25 | C25: Eva | D25: North | E25: Electronics | F25: Phone | G25: 6 | H25: 600 | I25: 20 | J25: =G25*H25*(1-I25/100) -> 2880 | K25: =G25*360 -> 2160 | L25: =J25-K25 -> 720
A26: 25 | B26: 2024-01-04 | C26: Carol | D26: East | E26: Food | F26: Tea | G26: 16 | H26: 10 | I26: 0 | J26: =G26*H26*(1-I26/100) -> 160 | K26: =G26*6 -> 96 | L26: =J26-K26 -> 64
A27: 26 | B27: 2024-02-03 | C27: David | D27: North | E27: Electronics | F27: Laptop | G27: 19 | H27: 1200 | I27: 0 | J27: =G27*H27*(1-I27/100) -> 22800 | K27: =G27*720 -> 13680 | L27: =J27-K27 -> 9120
A28: 27 | B28: 2024-02-18 | C28: Bob | D28: East | E28: Food | F28: Coffee | G28: 5 | H28: 15 | I28: 15 | J28: =G28*H28*(1-I28/100) -> 63.75 | K28: =G28*9 -> 45 | L28: =J28-K28 -> 18.75
A29: 28 | B29: 2024-02-18 | C29: Bob | D29: East | E29: Food | F29: Cookies | G29: 14 | H29: 8 | I29: 5 | J29: =G29*H29*(1-I29/100) -> 106.4 | K29: =G29*4.8 -> 67.2 | L29: =J29-K29 -> 39.2
A30: 29 | B30: 2024-02-17 | C30: David | D30: North | E30: Clothing | F30: Jacket | G30: 12 | H30: 120 | I30: 15 | J30: =G30*H30*(1-I30/100) -> 1224 | K30: =G30*72 -> 864 | L30: =J30-K30 -> 360
A31: 30 | B31: 2024-02-01 | C31: Eva | D31: South | E31: Electronics | F31: Laptop | G31: 3 | H31: 1200 | I31: 10 | J31: =G31*H31*(1-I31/100) -> 3240 | K31: =G31*720 -> 2160 | L31: =J31-K31 -> 1080
A32: 31 | B32: 2024-02-23 | C32: Alice | D32: South | E32: Food | F32: Coffee | G32: 1 | H32: 15 | I32: 0 | J32: =G32*H32*(1-I32/100) -> 15 | K32: =G32*9 -> 9 | L32: =J32-K32 -> 6
A33: 32 | B33: 2024-02-17 | C33: Bob | D33: East | E33: Electronics | F33: Laptop | G33: 11 | H33: 1200 | I33: 0 | J33: =G33*H33*(1-I33/100) -> 13200 | K33: =G33*720 -> 7920 | L33: =J33-K33 -> 5280
A34: 33 | B34: 2024-02-05 | C34: Eva | D34: West | E34: Food | F34: Tea | G34: 7 | H34: 10 | I34: 20 | J34: =G34*H34*(1-I34/100) -> 56 | K34: =G34*6 -> 42 | L34: =J34-K34 -> 14
A35: 34 | B35: 2024-02-04 | C35: Alice | D35: West | E35: Electronics | F35: Phone | G35: 14 | H35: 600 | I35: 5 | J35: =G35*H35*(1-I35/100) -> 7980 | K35: =G35*360 -> 5040 | L35: =J35-K35 -> 2940
A36: 35 | B36: 2024-02-28 | C36: Alice | D36: North | E36: Clothing | F36: Jeans | G36: 14 | H36: 60 | I36: 15 | J36: =G36*H36*(1-I36/100) -> 714 | K36: =G36*36 -> 504 | L36: =J36-K36 -> 210
A37: 36 | B37: 2024-02-08 | C37: Bob | D37: South | E37: Electronics | F37: Phone | G37: 11 | H37: 600 | I37: 0 | J37: =G37*H37*(1-I37/100) -> 6600 | K37: =G37*360 -> 3960 | L37: =J37-K37 -> 2640
A38: 37 | B38: 2024-02-06 | C38: Carol | D38: West | E38: Food | F38: Tea | G38: 5 | H38: 10 | I38: 15 | J38: =G38*H38*(1-I38/100) -> 42.5 | K38: =G38*6 -> 30 | L38: =J38-K38 -> 12.5
A39: 38 | B39: 2024-02-04 | C39: Alice | D39: North | E39: Electronics | F39: Laptop | G39: 15 | H39: 1200 | I39: 20 | J39: =G39*H39*(1-I39/100) -> 14400 | K39: =G39*720 -> 10800 | L39: =J39-K39 -> 3600
A40: 39 | B40: 2024-02-16 | C40: David | D40: South | E40: Electronics | F40: Laptop | G40: 6 | H40: 1200 | I40: 15 | J40: =G40*H40*(1-I40/100) -> 6120 | K40: =G40*720 -> 4320 | L40: =J40-K40 -> 1800
A41: 40 | B41: 2024-02-01 | C41: David | D41: East | E41: Clothing | F41: T-Shirt | G41: 6 | H41: 25 | I41: 15 | J41: =G41*H41*(1-I41/100) -> 127.5 | K41: =G41*15 -> 90 | L41: =J41-K41 -> 37.5
A42: 41 | B42: 2024-02-22 | C42: David | D42: South | E42: Clothing | F42: Jeans | G42: 14 | H42: 60 | I42: 20 | J42: =G42*H42*(1-I42/100) -> 672 | K42: =G42*36 -> 504 | L42: =J42-K42 -> 168
A43: 42 | B43: 2024-02-19 | C43: Eva | D43: North | E43: Electronics | F43: Phone | G43: 7 | H43: 600 | I43: 0 | J43: =G43*H43*(1-I43/100) -> 4200 | K43: =G43*360 -> 2520 | L43: =J43-K43 -> 1680
A44: 43 | B44: 2024-02-19 | C44: David | D44: South | E44: Food | F44: Tea | G44: 2 | H44: 10 | I44: 0 | J44: =G44*H44*(1-I44/100) -> 20 | K44: =G44*6 -> 12 | L44: =J44-K44 -> 8
A45: 44 | B45: 2024-03-20 | C45: Alice | D45: South | E45: Food | F45: Coffee | G45: 6 | H45: 15 | I45: 0 | J45: =G45*H45*(1-I45/100) -> 90 | K45: =G45*9 -> 54 | L45: =J45-K45 -> 36
A46: 45 | B46: 2024-03-19 | C46: Eva | D46: North | E46: Clothing | F46: T-Shirt | G46: 19 | H46: 25 | I46: 5 | J46: =G46*H46*(1-I46/100) -> 451.25 | K46: =G46*15 -> 285 | L46: =J46-K46 -> 166.25
A47: 46 | B47: 2024-03-19 | C47: Eva | D47: East | E47: Food | F47: Coffee | G47: 14 | H47: 15 | I47: 20 | J47: =G47*H47*(1-I47/100) -> 168 | K47: =G47*9 -> 126 | L47: =J47-K47 -> 42
A48: 47 | B48: 2024-03-09 | C48: David | D48: South | E48: Clothing | F48: T-Shirt | G48: 11 | H48: 25 | I48: 5 | J48: =G48*H48*(1-I48/100) -> 261.25 | K48: =G48*15 -> 165 | L48: =J48-K48 -> 96.25
A49: 48 | B49: 2024-03-11 | C49: Alice | D49: North | E49: Food | F49: Cookies | G49: 10 | H49: 8 | I49: 15 | J49: =G49*H49*(1-I49/100) -> 68 | K49: =G49*4.8 -> 48 | L49: =J49-K49 -> 20
A50: 49 | B50: 2024-03-03 | C50: Eva | D50: South | E50: Clothing | F50: Jacket | G50: 19 | H50: 120 | I50: 0 | J50: =G50*H50*(1-I50/100) -> 2280 | K50: =G50*72 -> 1368 | L50: =J50-K50 -> 912
A51: 50 | B51: 2024-03-03 | C51: Bob | D51: East | E51: Food | F51: Tea | G51: 5 | H51: 10 | I51: 10 | J51: =G51*H51*(1-I51/100) -> 45 | K51: =G51*6 -> 30 | L51: =J51-K51 -> 15
A52: 51 | B52: 2024-03-23 | C52: Carol | D52: North | E52: Clothing | F52: T-Shirt | G52: 15 | H52: 25 | I52: 20 | J52: =G52*H52*(1-I52/100) -> 300 | K52: =G52*15 -> 225 | L52: =J52-K52 -> 75
A53: 52 | B53: 2024-03-05 | C53: Carol | D53: North | E53: Food | F53: Cookies | G53: 10 | H53: 8 | I53: 0 | J53: =G53*H53*(1-I53/100) -> 80 | K53: =G53*4.8 -> 48 | L53: =J53-K53 -> 32
A54: 53 | B54: 2024-03-09 | C54: Carol | D54: South | E54: Electronics | F54: Tablet | G54: 18 | H54: 400 | I54: 5 | J54: =G54*H54*(1-I54/100) -> 6840 | K54: =G54*240 -> 4320 | L54: =J54-K54 -> 2520
A55: 54 | B55: 2024-03-17 | C55: David | D55: East | E55: Food | F55: Tea | G55: 7 | H55: 10 | I55: 10 | J55: =G55*H55*(1-I55/100) -> 63 | K55: =G55*6 -> 42 | L55: =J55-K55 -> 21
A56: 55 | B56: 2024-03-02 | C56: Alice | D56: East | E56: Electronics | F56: Laptop | G56: 14 | H56: 1200 | I56: 10 | J56: =G56*H56*(1-I56/100) -> 15120 | K56: =G56*720 -> 10080 | L56: =J56-K56 -> 5040
A57: 56 | B57: 2024-03-24 | C57: David | D57: West | E57: Electronics | F57: Tablet | G57: 9 | H57: 400 | I57: 5 | J57: =G57*H57*(1-I57/100) -> 3420 | K57: =G57*240 -> 2160 | L57: =J57-K57 -> 1260
A58: 57 | B58: 2024-03-23 | C58: Bob | D58: North | E58: Food | F58: Coffee | G58: 4 | H58: 15 | I58: 0 | J58: =G58*H58*(1-I58/100) -> 60 | K58: =G58*9 -> 36 | L58: =J58-K58 -> 24
A59: 58 | B59: 2024-03-14 | C59: Bob | D59: North | E59: Clothing | F59: Jacket | G59: 18 | H59: 120 | I59: 5 | J59: =G59*H59*(1-I59/100) -> 2052 | K59: =G59*72 -> 1296 | L59: =J59-K59 -> 756
A60: 59 | B60: 2024-04-22 | C60: Bob | D60: North | E60: Clothing | F60: T-Shirt | G60: 12 | H60: 25 | I60: 5 | J60: =G60*H60*(1-I60/100) -> 285 | K60: =G60*15 -> 180 | L60: =J60-K60 -> 105
A61: 60 | B61: 2024-04-24 | C61: Bob | D61: South | E61: Clothing | F61: Jacket | G61: 14 | H61: 120 | I61: 20 | J61: =G61*H61*(1-I61/100) -> 1344 | K61: =G61*72 -> 1008 | L61: =J61-K61 -> 336
A62: 61 | B62: 2024-04-06 | C62: Carol | D62: West | E62: Electronics | F62: Laptop | G62: 14 | H62: 1200 | I62: 0 | J62: =G62*H62*(1-I62/100) -> 16800 | K62: =G62*720 -> 10080 | L62: =J62-K62 -> 6720
A63: 62 | B63: 2024-04-06 | C63: Alice | D63: West | E63: Food | F63: Cookies | G63: 8 | H63: 8 | I63: 10 | J63: =G63*H63*(1-I63/100) -> 57.6 | K63: =G63*4.8 -> 38.4 | L63: =J63-K63 -> 19.2
A64: 63 | B64: 2024-04-27 | C64: David | D64: East | E64: Electronics | F64: Phone | G64: 8 | H64: 600 | I64: 5 | J64: =G64*H64*(1-I64/100) -> 4560 | K64: =G64*360 -> 2880 | L64: =J64-K64 -> 1680
A65: 64 | B65: 2024-04-22 | C65: Bob | D65: West | E65: Clothing | F65: T-Shirt | G65: 8 | H65: 25 | I65: 0 | J65: =G65*H65*(1-I65/100) -> 200 | K65: =G65*15 -> 120 | L65: =J65-K65 -> 80
A66: 65 | B66: 2024-04-12 | C66: Eva | D66: West | E66: Clothing | F66: Jeans | G66: 3 | H66: 60 | I66: 10 | J66: =G66*H66*(1-I66/100) -> 162 | K66: =G66*36 -> 108 | L66: =J66-K66 -> 54
A67: 66 | B67: 2024-04-04 | C67: Carol | D67: South | E67: Food | F67: Cookies | G67: 11 | H67: 8 | I67: 0 | J67: =G67*H67*(1-I67/100) -> 88 | K67: =G67*4.8 -> 52.8 | L67: =J67-K67 -> 35.2
A68: 67 | B68: 2024-04-20 | C68: David | D68: East | E68: Food | F68: Tea | G68: 2 | H68: 10 | I68: 0 | J68: =G68*H68*(1-I68/100) -> 20 | K68: =G68*6 -> 12 | L68: =J68-K68 -> 8
A69: 68 | B69: 2024-04-17 | C69: Alice | D69: West | E69: Food | F69: Tea | G69: 14 | H69: 10 | I69: 20 | J69: =G69*H69*(1-I69/100) -> 112 | K69: =G69*6 -> 84 | L69: =J69-K69 -> 28
A70: 69 | B70: 2024-04-23 | C70: David | D70: North | E70: Food | F70: Coffee | G70: 9 | H70: 15 | I70: 0 | J70: =G70*H70*(1-I70/100) -> 135 | K70: =G70*9 -> 81 | L70: =J70-K70 -> 54
A71: 70 | B71: 2024-04-14 | C71: Alice | D71: East | E71: Food | F71: Cookies | G71: 7 | H71: 8 | I71: 10 | J71: =G71*H71*(1-I71/100) -> 50.4 | K71: =G71*4.8 -> 33.6 | L71: =J71-K71 -> 16.8
A72: 71 | B72: 2024-04-17 | C72: Carol | D72: West | E72: Food | F72: Tea | G72: 4 | H72: 10 | I72: 10 | J72: =G72*H72*(1-I72/100) -> 36 | K72: =G72*6 -> 24 | L72: =J72-K72 -> 12
A73: 72 | B73: 2024-04-05 | C73: Bob | D73: West | E73: Clothing | F73: Jeans | G73: 10 | H73: 60 | I73: 20 | J73: =G73*H73*(1-I73/100) -> 480 | K73: =G73*36 -> 360 | L73: =J73-K73 -> 120
A74: 73 | B74: 2024-04-19 | C74: Carol | D74: West | E74: Food | F74: Tea | G74: 6 | H74: 10 | I74: 20 | J74: =G74*H74*(1-I74/100) -> 48 | K74: =G74*6 -> 36 | L74: =J74-K74 -> 12
A75: 74 | B75: 2024-04-07 | C75: David | D75: East | E75: Food | F75: Coffee | G75: 10 | H75: 15 | I75: 10 | J75: =G75*H75*(1-I75/100) -> 135 | K75: =G75*9 -> 90 | L75: =J75-K75 -> 45
A76: 75 | B76: 2024-04-17 | C76: David | D76: South | E76: Clothing | F76: Jeans | G76: 15 | H76: 60 | I76: 5 | J76: =G76*H76*(1-I76/100) -> 855 | K76: =G76*36 -> 540 | L76: =J76-K76 -> 315
A77: 76 | B77: 2024-04-22 | C77: Eva | D77: East | E77: Food | F77: Coffee | G77: 10 | H77: 15 | I77: 20 | J77: =G77*H77*(1-I77/100) -> 120 | K77: =G77*9 -> 90 | L77: =J77-K77 -> 30
A78: 77 | B78: 2024-04-26 | C78: Bob | D78: South | E78: Electronics | F78: Laptop | G78: 10 | H78: 1200 | I78: 5 | J78: =G78*H78*(1-I78/100) -> 11400 | K78: =G78*720 -> 7200 | L78: =J78-K78 -> 4200
A79: 78 | B79: 2024-05-28 | C79: Alice | D79: West | E79: Electronics | F79: Laptop | G79: 16 | H79: 1200 | I79: 20 | J79: =G79*H79*(1-I79/100) -> 15360 | K79: =G79*720 -> 11520 | L79: =J79-K79 -> 3840
A80: 79 | B80: 2024-05-23 | C80: David | D80: West | E80: Clothing | F80: Jacket | G80: 19 | H80: 120 | I80: 5 | J80: =G80*H80*(1-I80/100) -> 2166 | K80: =G80*72 -> 1368 | L80: =J80-K80 -> 798
A81: 80 | B81: 2024-05-25 | C81: Alice | D81: West | E81: Clothing | F81: T-Shirt | G81: 5 | H81: 25 | I81: 0 | J81: =G81*H81*(1-I81/100) -> 125 | K81: =G81*15 -> 75 | L81: =J81-K81 -> 50
A82: 81 | B82: 2024-05-02 | C82: Eva | D82: South | E82: Electronics | F82: Laptop | G82: 17 | H82: 1200 | I82: 15 | J82: =G82*H82*(1-I82/100) -> 17340 | K82: =G82*720 -> 12240 | L82: =J82-K82 -> 5100
A83: 82 | B83: 2024-05-22 | C83: Eva | D83: East | E83: Electronics | F83: Phone | G83: 5 | H83: 600 | I83: 15 | J83: =G83*H83*(1-I83/100) -> 2550 | K83: =G83*360 -> 1800 | L83: =J83-K83 -> 750
A84: 83 | B84: 2024-05-27 | C84: Eva | D84: West | E84: Clothing | F84: Jacket | G84: 17 | H84: 120 | I84: 15 | J84: =G84*H84*(1-I84/100) -> 1734 | K84: =G84*72 -> 1224 | L84: =J84-K84 -> 510
A85: 84 | B85: 2024-05-09 | C85: Bob | D85: East | E85: Electronics | F85: Tablet | G85: 16 | H85: 400 | I85: 15 | J85: =G85*H85*(1-I85/100) -> 5440 | K85: =G85*240 -> 3840 | L85: =J85-K85 -> 1600
A86: 85 | B86: 2024-05-15 | C86: Alice | D86: East | E86: Food | F86: Tea | G86: 8 | H86: 10 | I86: 10 | J86: =G86*H86*(1-I86/100) -> 72 | K86: =G86*6 -> 48 | L86: =J86-K86 -> 24
A87: 86 | B87: 2024-05-18 | C87: Alice | D87: South | E87: Electronics | F87: Phone | G87: 11 | H87: 600 | I87: 10 | J87: =G87*H87*(1-I87/100) -> 5940 | K87: =G87*360 -> 3960 | L87: =J87-K87 -> 1980
A88: 87 | B88: 2024-05-23 | C88: Bob | D88: North | E88: Electronics | F88: Laptop | G88: 13 | H88: 1200 | I88: 5 | J88: =G88*H88*(1-I88/100) -> 14820 | K88: =G88*720 -> 9360 | L88: =J88-K88 -> 5460
A89: 88 | B89: 2024-05-15 | C89: David | D89: North | E89: Clothing | F89: Jeans | G89: 11 | H89: 60 | I89: 20 | J89: =G89*H89*(1-I89/100) -> 528 | K89: =G89*36 -> 396 | L89: =J89-K89 -> 132
A90: 89 | B90: 2024-05-23 | C90: Alice | D90: West | E90: Electronics | F90: Phone | G90: 13 | H90: 600 | I90: 20 | J90: =G90*H90*(1-I90/100) -> 6240 | K90: =G90*360 -> 4680 | L90: =J90-K90 -> 1560
A91: 90 | B91: 2024-05-25 | C91: David | D91: West | E91: Clothing | F91: T-Shirt | G91: 12 | H91: 25 | I91: 10 | J91: =G91*H91*(1-I91/100) -> 270 | K91: =G91*15 -> 180 | L91: =J91-K91 -> 90
A92: 91 | B92: 2024-05-08 | C92: David | D92: South | E92: Food | F92: Cookies | G92: 18 | H92: 8 | I92: 20 | J92: =G92*H92*(1-I92/100) -> 115.2 | K92: =G92*4.8 -> 86.4 | L92: =J92-K92 -> 28.8
A93: 92 | B93: 2024-05-13 | C93: Carol | D93: West | E93: Clothing | F93: Jeans | G93: 16 | H93: 60 | I93: 0 | J93: =G93*H93*(1-I93/100) -> 960 | K93: =G93*36 -> 576 | L93: =J93-K93 -> 384
A94: 93 | B94: 2024-06-01 | C94: David | D94: North | E94: Clothing | F94: T-Shirt | G94: 20 | H94: 25 | I94: 20 | J94: =G94*H94*(1-I94/100) -> 400 | K94: =G94*15 -> 300 | L94: =J94-K94 -> 100
A95: 94 | B95: 2024-06-28 | C95: David | D95: South | E95: Electronics | F95: Tablet | G95: 14 | H95: 400 | I95: 5 | J95: =G95*H95*(1-I95/100) -> 5320 | K95: =G95*240 -> 3360 | L95: =J95-K95 -> 1960
A96: 95 | B96: 2024-06-07 | C96: David | D96: East | E96: Electronics | F96: Phone | G96: 13 | H96: 600 | I96: 10 | J96: =G96*H96*(1-I96/100) -> 7020 | K96: =G96*360 -> 4680 | L96: =J96-K96 -> 2340
A97: 96 | B97: 2024-06-09 | C97: Alice | D97: West | E97: Clothing | F97: Jeans | G97: 9 | H97: 60 | I97: 15 | J97: =G97*H97*(1-I97/100) -> 459 | K97: =G97*36 -> 324 | L97: =J97-K97 -> 135
A98: 97 | B98: 2024-06-12 | C98: Bob | D98: North | E98: Electronics | F98: Tablet | G98: 18 | H98: 400 | I98: 0 | J98: =G98*H98*(1-I98/100) -> 7200 | K98: =G98*240 -> 4320 | L98: =J98-K98 -> 2880
A99: 98 | B99: 2024-06-07 | C99: Alice | D99: South | E99: Food | F99: Coffee | G99: 1 | H99: 15 | I99: 5 | J99: =G99*H99*(1-I99/100) -> 14.25 | K99: =G99*9 -> 9 | L99: =J99-K99 -> 5.25
A100: 99 | B100: 2024-06-19 | C100: Bob | D100: West | E100: Electronics | F100: Laptop | G100: 16 | H100: 1200 | I100: 0 | J100: =G100*H100*(1-I100/100) -> 19200 | K100: =G100*720 -> 11520 | L100: =J100-K100 -> 7680
...

Sheet Summary
A1: OVERALL KPIs | D1: Revenue by Category | I1: Revenue by Salesperson
D2: Category | E2: Revenue | F2: Profit | G2: % of Total | I2: Salesperson | J2: Revenue | K2: Orders | L2: Avg/Order | M2: Rank
A3: Total Orders | B3: =COUNTA(Sales_Data!A2:A230) -> 229 | D3: Electronics | E3: =SUMIF(Sales_Data!E2:E230,D3,Sales_Data!J2:J230) -> 594990 | F3: =SUMIF(Sales_Data!E2:E230,D3,Sales_Data!L2:L230) -> 201870 | G3: =E3/$B$4 -> 0.90615765 | I3: Alice | J3: =SUMIF(Sales_Data!C2:C230,I3,Sales_Data!J2:J230) -> 157613.8 | K3: =COUNTIF(Sales_Data!C2:C230,I3) -> 45 | L3: =J3/K3 -> 3502.5289 | M3: =RANK(J3,J3:J7,0) -> 2
A4: Total Revenue | B4: =SUM(Sales_Data!J2:J230) -> 656607.6 | D4: Clothing | E4: =SUMIF(Sales_Data!E2:E230,D4,Sales_Data!J2:J230) -> 53895.5 | F4: =SUMIF(Sales_Data!E2:E230,D4,Sales_Data!L2:L230) -> 17385.5 | G4: =E4/$B$4 -> 0.082081749 | I4: Bob | J4: =SUMIF(Sales_Data!C2:C230,I4,Sales_Data!J2:J230) -> 219516.2 | K4: =COUNTIF(Sales_Data!C2:C230,I4) -> 46 | L4: =J4/K4 -> 4772.0913 | M4: =RANK(J4,J3:J7,0) -> 1
A5: Total Cost | B5: =SUM(Sales_Data!K2:K230) -> 434722.8 | D5: Food | E5: =SUMIF(Sales_Data!E2:E230,D5,Sales_Data!J2:J230) -> 7722.1 | F5: =SUMIF(Sales_Data!E2:E230,D5,Sales_Data!L2:L230) -> 2629.3 | G5: =E5/$B$4 -> 0.011760601 | I5: Carol | J5: =SUMIF(Sales_Data!C2:C230,I5,Sales_Data!J2:J230) -> 111148.75 | K5: =COUNTIF(Sales_Data!C2:C230,I5) -> 48 | L5: =J5/K5 -> 2315.599 | M5: =RANK(J5,J3:J7,0) -> 3
A6: Total Profit | B6: =SUM(Sales_Data!L2:L230) -> 221884.8 | I6: David | J6: =SUMIF(Sales_Data!C2:C230,I6,Sales_Data!J2:J230) -> 97822.65 | K6: =COUNTIF(Sales_Data!C2:C230,I6) -> 53 | L6: =J6/K6 -> 1845.7104 | M6: =RANK(J6,J3:J7,0) -> 4
A7: Avg Order Value | B7: =B4/B3 -> 2867.2821 | I7: Eva | J7: =SUMIF(Sales_Data!C2:C230,I7,Sales_Data!J2:J230) -> 70506.2 | K7: =COUNTIF(Sales_Data!C2:C230,I7) -> 37 | L7: =J7/K7 -> 1905.573 | M7: =RANK(J7,J3:J7,0) -> 5
A8: Avg Discount % | B8: =AVERAGEIF(Sales_Data!I2:I230,">0",Sales_Data!I2:I230) -> 12.445055
A9: Profit Margin % | B9: =B6/B4 -> 0.33792603
A12: Monthly Revenue Trend
A13: Month | B13: Revenue | C13: Profit | D13: MoM Growth %
A14: 2024-01 | B14: =SUMPRODUCT((TEXT(Sales_Data!B2:B230,"yyyy-mm")=A14)*Sales_Data!J2:J230) -> 84277.15 | C14: =SUMPRODUCT((TEXT(Sales_Data!B2:B230,"yyyy-mm")=A14)*Sales_Data!L2:L230) -> 28318.75 | D14: -
A15: 2024-02 | B15: =SUMPRODUCT((TEXT(Sales_Data!B2:B230,"yyyy-mm")=A15)*Sales_Data!J2:J230) -> 81581.15 | C15: =SUMPRODUCT((TEXT(Sales_Data!B2:B230,"yyyy-mm")=A15)*Sales_Data!L2:L230) -> 29013.95 | D15: =(B15-B14)/B14 -> -0.031989691
A16: 2024-03 | B16: =SUMPRODUCT((TEXT(Sales_Data!B2:B230,"yyyy-mm")=A16)*Sales_Data!J2:J230) -> 31298.5 | C16: =SUMPRODUCT((TEXT(Sales_Data!B2:B230,"yyyy-mm")=A16)*Sales_Data!L2:L230) -> 11015.5 | D16: =(B16-B15)/B15 -> -0.61635133
A17: 2024-04 | B17: =SUMPRODUCT((TEXT(Sales_Data!B2:B230,"yyyy-mm")=A17)*Sales_Data!J2:J230) -> 36888 | C17: =SUMPRODUCT((TEXT(Sales_Data!B2:B230,"yyyy-mm")=A17)*Sales_Data!L2:L230) -> 13870.2 | D17: =(B17-B16)/B16 -> 0.17858683
A18: 2024-05 | B18: =SUMPRODUCT((TEXT(Sales_Data!B2:B230,"yyyy-mm")=A18)*Sales_Data!J2:J230) -> 73660.2 | C18: =SUMPRODUCT((TEXT(Sales_Data!B2:B230,"yyyy-mm")=A18)*Sales_Data!L2:L230) -> 22306.8 | D18: =(B18-B17)/B17 -> 0.99686077
A19: 2024-06 | B19: =SUMPRODUCT((TEXT(Sales_Data!B2:B230,"yyyy-mm")=A19)*Sales_Data!J2:J230) -> 54268.65 | C19: =SUMPRODUCT((TEXT(Sales_Data!B2:B230,"yyyy-mm")=A19)*Sales_Data!L2:L230) -> 20541.45 | D19: =(B19-B18)/B18 -> -0.26325682
A20: 2024-07 | B20: =SUMPRODUCT((TEXT(Sales_Data!B2:B230,"yyyy-mm")=A20)*Sales_Data!J2:J230) -> 50175.1 | C20: =SUMPRODUCT((TEXT(Sales_Data!B2:B230,"yyyy-mm")=A20)*Sales_Data!L2:L230) -> 17213.5 | D20: =(B20-B19)/B19 -> -0.075431211
A21: 2024-08 | B21: =SUMPRODUCT((TEXT(Sales_Data!B2:B230,"yyyy-mm")=A21)*Sales_Data!J2:J230) -> 25859.1 | C21: =SUMPRODUCT((TEXT(Sales_Data!B2:B230,"yyyy-mm")=A21)*Sales_Data!L2:L230) -> 7814.7 | D21: =(B21-B20)/B20 -> -0.48462285
A22: 2024-09 | B22: =SUMPRODUCT((TEXT(Sales_Data!B2:B230,"yyyy-mm")=A22)*Sales_Data!J2:J230) -> 17162.75 | C22: =SUMPRODUCT((TEXT(Sales_Data!B2:B230,"yyyy-mm")=A22)*Sales_Data!L2:L230) -> 5577.35 | D22: =(B22-B21)/B21 -> -0.33629747
A23: 2024-10 | B23: =SUMPRODUCT((TEXT(Sales_Data!B2:B230,"yyyy-mm")=A23)*Sales_Data!J2:J230) -> 63523.35 | C23: =SUMPRODUCT((TEXT(Sales_Data!B2:B230,"yyyy-mm")=A23)*Sales_Data!L2:L230) -> 18847.95 | D23: =(B23-B22)/B22 -> 2.7012338
A24: 2024-11 | B24: =SUMPRODUCT((TEXT(Sales_Data!B2:B230,"yyyy-mm")=A24)*Sales_Data!J2:J230) -> 30298.25 | C24: =SUMPRODUCT((TEXT(Sales_Data!B2:B230,"yyyy-mm")=A24)*Sales_Data!L2:L230) -> 10960.25 | D24: =(B24-B23)/B23 -> -0.52303759
A25: 2024-12 | B25: =SUMPRODUCT((TEXT(Sales_Data!B2:B230,"yyyy-mm")=A25)*Sales_Data!J2:J230) -> 107615.4 | C25: =SUMPRODUCT((TEXT(Sales_Data!B2:B230,"yyyy-mm")=A25)*Sales_Data!L2:L230) -> 36404.4 | D25: =(B25-B24)/B24 -> 2.5518685

Sheet Region_Category
A1: Revenue by Region × Category
A2: Region / Category | B2: Electronics | C2: Clothing | D2: Food | E2: Total
A3: North | B3: =SUMPRODUCT((Sales_Data!D2:D230=A3)*(Sales_Data!E2:E230="Electronics")*Sales_Data!J2:J230) -> 195690 | C3: =SUMPRODUCT((Sales_Data!D2:D230=A3)*(Sales_Data!E2:E230="Clothing")*Sales_Data!J2:J230) -> 20598 | D3: =SUMPRODUCT((Sales_Data!D2:D230=A3)*(Sales_Data!E2:E230="Food")*Sales_Data!J2:J230) -> 1704.8 | E3: =SUM(B3:D3) -> 217992.8
A4: South | B4: =SUMPRODUCT((Sales_Data!D2:D230=A4)*(Sales_Data!E2:E230="Electronics")*Sales_Data!J2:J230) -> 141740 | C4: =SUMPRODUCT((Sales_Data!D2:D230=A4)*(Sales_Data!E2:E230="Clothing")*Sales_Data!J2:J230) -> 9855.25 | D4: =SUMPRODUCT((Sales_Data!D2:D230=A4)*(Sales_Data!E2:E230="Food")*Sales_Data!J2:J230) -> 1806.85 | E4: =SUM(B4:D4) -> 153402.1
A5: East | B5: =SUMPRODUCT((Sales_Data!D2:D230=A5)*(Sales_Data!E2:E230="Electronics")*Sales_Data!J2:J230) -> 122610 | C5: =SUMPRODUCT((Sales_Data!D2:D230=A5)*(Sales_Data!E2:E230="Clothing")*Sales_Data!J2:J230) -> 9706 | D5: =SUMPRODUCT((Sales_Data!D2:D230=A5)*(Sales_Data!E2:E230="Food")*Sales_Data!J2:J230) -> 2876 | E5: =SUM(B5:D5) -> 135192
A6: West | B6: =SUMPRODUCT((Sales_Data!D2:D230=A6)*(Sales_Data!E2:E230="Electronics")*Sales_Data!J2:J230) -> 134950 | C6: =SUMPRODUCT((Sales_Data!D2:D230=A6)*(Sales_Data!E2:E230="Clothing")*Sales_Data!J2:J230) -> 13736.25 | D6: =SUMPRODUCT((Sales_Data!D2:D230=A6)*(Sales_Data!E2:E230="Food")*Sales_Data!J2:J230) -> 1334.45 | E6: =SUM(B6:D6) -> 150020.7
A7: Grand Total | B7: =SUM(B3:B6) -> 594990 | C7: =SUM(C3:C6) -> 53895.5 | D7: =SUM(D3:D6) -> 7722.1 | E7: =SUM(E3:E6) -> 656607.6
